{
    "id": 12624008,
    "name": "Radiant Spirit",
    "type": "Effect Monster",
    "desc": "When this card is destroyed by battle and sent to the Graveyard, destroy all face-down and non-LIGHT monsters.",
    "atk": 2000,
    "def": 1500,
    "level": 7,
    "race": "Reptile",
    "attribute": "LIGHT",
    "scale": null,
    "archetype": null,
    "linkval": null,
    "linkmarkers": null,
    "image_url": "https://images.ygoprodeck.com/images/cards/12624008.jpg",
    "image_url_small": "https://images.ygoprodeck.com/images/cards_small/12624008.jpg",
    "image_url_cropped": "https://images.ygoprodeck.com/images/cards_cropped/12624008.jpg"
}