{
    "id": 100438037,
    "name": "Apodrakosis Ascension Gate of Dinocrag",
    "type": "Spell Card",
    "desc": "You can only control 1 \"Apodrakosis Ascension Gate of Dinocrag\". \"Apodrakosis\" monsters you control gain 300 ATK. \"Apodrakosis\" Pendulum Monsters, and Level 10 or higher monsters whose original Type is Dinosaur, you control gain this effect.\r\n\u25cf Once per turn, when the effect of a monster on the field with less ATK than this card is activated (Quick Effect): You can place 1 face-up \"Apodrakosis\" Continuous Spell you control on the bottom of the Deck; negate the activation.",
    "atk": null,
    "def": null,
    "level": null,
    "race": "Continuous",
    "attribute": null,
    "scale": null,
    "archetype": "Apodrakosis",
    "linkval": null,
    "linkmarkers": null,
    "image_url": "https://images.ygoprodeck.com/images/cards/100438037.jpg",
    "image_url_small": "https://images.ygoprodeck.com/images/cards_small/100438037.jpg",
    "image_url_cropped": "https://images.ygoprodeck.com/images/cards_cropped/100438037.jpg"
}