{
    "id": 24027078,
    "name": "Morgan, the Enchantress of Avalon",
    "type": "Effect Monster",
    "desc": "When your opponent activates a card or effect, while you control a \"Noble Knight\" monster and a \"Noble Arms\" Equip Spell (Quick Effect): You can send this card from your hand to the GY; destroy 1 \"Noble Arms\" Equip Spell you control, and if you do, negate the activation. You can only use this effect of \"Morgan, the Enchantress of Avalon\" once per turn.",
    "atk": 1300,
    "def": 1600,
    "level": 3,
    "race": "Spellcaster",
    "attribute": "DARK",
    "scale": null,
    "archetype": "Noble Knight",
    "linkval": null,
    "linkmarkers": null,
    "image_url": "https://images.ygoprodeck.com/images/cards/24027078.jpg",
    "image_url_small": "https://images.ygoprodeck.com/images/cards_small/24027078.jpg",
    "image_url_cropped": "https://images.ygoprodeck.com/images/cards_cropped/24027078.jpg"
}