{
    "id": 12469386,
    "name": "Revival Rose",
    "type": "Effect Monster",
    "desc": "If a Level 5 or higher Plant-Type monster you control is destroyed, you can Special Summon this card from the Graveyard.",
    "atk": 1300,
    "def": 1300,
    "level": 4,
    "race": "Plant",
    "attribute": "DARK",
    "scale": null,
    "archetype": "Rose Dragon",
    "linkval": null,
    "linkmarkers": null,
    "image_url": "https://images.ygoprodeck.com/images/cards/12469386.jpg",
    "image_url_small": "https://images.ygoprodeck.com/images/cards_small/12469386.jpg",
    "image_url_cropped": "https://images.ygoprodeck.com/images/cards_cropped/12469386.jpg"
}