{
    "id": 7625614,
    "name": "Raregold Armor",
    "type": "Spell Card",
    "desc": "As long as you control the monster equipped with this card, your opponent cannot attack other monsters other than the equipped monster.",
    "atk": null,
    "def": null,
    "level": null,
    "race": "Equip",
    "attribute": null,
    "scale": null,
    "archetype": null,
    "linkval": null,
    "linkmarkers": null,
    "image_url": "https://images.ygoprodeck.com/images/cards/7625614.jpg",
    "image_url_small": "https://images.ygoprodeck.com/images/cards_small/7625614.jpg",
    "image_url_cropped": "https://images.ygoprodeck.com/images/cards_cropped/7625614.jpg"
}