{
    "id": 1006081,
    "name": "Junk Changer",
    "type": "Tuner Monster",
    "desc": "You can only use the following effect of \"Junk Changer\" once per turn. If this card is Normal or Special Summoned: You can target 1 \"Junk\" monster on the field, then activate 1 of these effects;\n\u25cf Increase its Level by 1.\n\u25cf Reduce its Level by 1.",
    "atk": 1500,
    "def": 900,
    "level": 3,
    "race": "Warrior",
    "attribute": "EARTH",
    "scale": null,
    "archetype": "Junk",
    "linkval": null,
    "linkmarkers": null,
    "image_url": "https://images.ygoprodeck.com/images/cards/1006081.jpg",
    "image_url_small": "https://images.ygoprodeck.com/images/cards_small/1006081.jpg",
    "image_url_cropped": "https://images.ygoprodeck.com/images/cards_cropped/1006081.jpg"
}