{
    "id": 100455002,
    "name": "Comic Cat",
    "typeline": [
        "Beast",
        "Effect"
    ],
    "type": "Effect Monster",
    "humanReadableCardType": "Effect Monster",
    "frameType": "effect",
    "desc": "This card is treated as a Toon monster while \"Toon World\" is on the field. During the Main Phase (Quick Effect): You can Tribute 1 monster (if you control \"Toon World\", you can Tribute 1 monster your opponent controls, even though you do not control it), and if you do, Special Summon 1 monster that mentions \"Toon World\" from your hand or Deck, ignoring its Summoning conditions. You can only use this effect of \"Comic Cat\" once per turn.",
    "race": "Beast",
    "atk": 0,
    "def": 0,
    "level": 1,
    "attribute": "DARK",
    "ygoprodeck_url": "https://ygoprodeck.com/card/comic-cat-15655",
    "card_images": [
        {
            "id": 100455002,
            "image_url": "https://images.ygoprodeck.com/images/cards/100455002.jpg",
            "image_url_small": "https://images.ygoprodeck.com/images/cards_small/100455002.jpg",
            "image_url_cropped": "https://images.ygoprodeck.com/images/cards_cropped/100455002.jpg"
        }
    ],
    "card_prices": [
        {
            "cardmarket_price": "0.00",
            "tcgplayer_price": "0.00",
            "ebay_price": "0.00",
            "amazon_price": "0.00",
            "coolstuffinc_price": "0.00"
        }
    ]
}