{
    "id": 57069605,
    "name": "Frozen Soul",
    "type": "Trap Card",
    "desc": "You can only activate this card when your Life Points are at least 2000 lower than your opponent's. Skip your opponent's next Battle Phase.",
    "atk": null,
    "def": null,
    "level": null,
    "race": "Normal",
    "attribute": null,
    "scale": null,
    "archetype": null,
    "linkval": null,
    "linkmarkers": null,
    "image_url": "https://images.ygoprodeck.com/images/cards/57069605.jpg",
    "image_url_small": "https://images.ygoprodeck.com/images/cards_small/57069605.jpg",
    "image_url_cropped": "https://images.ygoprodeck.com/images/cards_cropped/57069605.jpg"
}