{
    "id": 44913552,
    "name": "Timeater",
    "type": "Effect Monster",
    "desc": "If this card destroys an opponent's monster by battle: Your opponent skips their next Main Phase 1.",
    "atk": 1900,
    "def": 1700,
    "level": 6,
    "race": "Machine",
    "attribute": "DARK",
    "scale": null,
    "archetype": null,
    "linkval": null,
    "linkmarkers": null,
    "image_url": "https://images.ygoprodeck.com/images/cards/44913552.jpg",
    "image_url_small": "https://images.ygoprodeck.com/images/cards_small/44913552.jpg",
    "image_url_cropped": "https://images.ygoprodeck.com/images/cards_cropped/44913552.jpg"
}