{
    "id": 99529628,
    "name": "Keaf, Murk of the Ghoti",
    "typeline": [
        "Fish",
        "Effect"
    ],
    "type": "Effect Monster",
    "humanReadableCardType": "Effect Monster",
    "frameType": "effect",
    "desc": "If a Fish monster is on the field: You can Special Summon this card from your hand. If a monster(s) is Special Summoned to your opponent's field (except during the Damage Step): You can target 1 of those monsters and 1 of your banished Level 6 or lower Fish monsters; banish both that opponent's monster and this card, and if you do, Special Summon your targeted monster. During the Standby Phase of the next turn after this card was banished: You can Special Summon this banished card. You can only use each effect of \"Keaf, Murk of the Ghoti\" once per turn.",
    "race": "Fish",
    "atk": 0,
    "def": 1500,
    "level": 2,
    "attribute": "WATER",
    "archetype": "Ghoti",
    "ygoprodeck_url": "https://ygoprodeck.com/card/keaf-murk-of-the-ghoti-14187",
    "card_sets": [
        {
            "set_name": "Phantom Nightmare",
            "set_code": "PHNI-EN015",
            "set_rarity": "Super Rare",
            "set_rarity_code": "(SR)",
            "set_price": "0"
        }
    ],
    "card_images": [
        {
            "id": 99529628,
            "image_url": "https://images.ygoprodeck.com/images/cards/99529628.jpg",
            "image_url_small": "https://images.ygoprodeck.com/images/cards_small/99529628.jpg",
            "image_url_cropped": "https://images.ygoprodeck.com/images/cards_cropped/99529628.jpg"
        }
    ],
    "card_prices": [
        {
            "cardmarket_price": "0.25",
            "tcgplayer_price": "0.35",
            "ebay_price": "0.00",
            "amazon_price": "0.00",
            "coolstuffinc_price": "0.00"
        }
    ]
}