{
    "id": 101402062,
    "name": "Clock Tower Prison City - Dark City",
    "type": "Spell Card",
    "humanReadableCardType": "Field Spell",
    "frameType": "spell",
    "desc": "Each time you Special Summon a Level 8 or higher \"Destiny HERO\" monster(s): All Warrior monsters you currently control gain 300 ATK. You can only use each of the following effects of \"Clock Tower Prison City - Dark City\" once per turn. During your Main Phase, if this card was activated this turn: You can add 1 \"Destiny HERO\" monster, or 1 card that mentions a \"Destiny HERO\" monster's card name, from your Deck to your hand. If this card is destroyed: You can Special Summon 1 \"Destiny HERO\" monster from your Deck (this is treated as a Special Summon with \"Clock Tower Prison\").",
    "race": "Field",
    "ygoprodeck_url": "https://ygoprodeck.com/card/clock-tower-prison-city-dark-city-15754",
    "card_images": [
        {
            "id": 101402062,
            "image_url": "https://images.ygoprodeck.com/images/cards/101402062.jpg",
            "image_url_small": "https://images.ygoprodeck.com/images/cards_small/101402062.jpg",
            "image_url_cropped": "https://images.ygoprodeck.com/images/cards_cropped/101402062.jpg"
        }
    ],
    "card_prices": [
        {
            "cardmarket_price": "0.00",
            "tcgplayer_price": "0.00",
            "ebay_price": "0.00",
            "amazon_price": "0.00",
            "coolstuffinc_price": "0.00"
        }
    ]
}