{
    "id": 23297235,
    "name": "Flamvell Firedog",
    "type": "Effect Monster",
    "desc": "When this card destroys an opponent's monster by battle and sends it to the GY: You can Special Summon 1 FIRE monster with 200 or less DEF from your Deck, except \"Flamvell Firedog\".",
    "atk": 1900,
    "def": 200,
    "level": 4,
    "race": "Beast",
    "attribute": "FIRE",
    "scale": null,
    "archetype": "Flamvell",
    "linkval": null,
    "linkmarkers": null,
    "image_url": "https://images.ygoprodeck.com/images/cards/23297235.jpg",
    "image_url_small": "https://images.ygoprodeck.com/images/cards_small/23297235.jpg",
    "image_url_cropped": "https://images.ygoprodeck.com/images/cards_cropped/23297235.jpg"
}