{
    "id": 11264180,
    "name": "TGX1-HL",
    "type": "Spell Card",
    "desc": "Target 1 \"T.G.\" monster you control; its ATK and DEF each become half its current ATK and DEF, and if they do, destroy 1 other Spell/Trap Card on the field.",
    "atk": null,
    "def": null,
    "level": null,
    "race": "Quick-Play",
    "attribute": null,
    "scale": null,
    "archetype": "T.G.",
    "linkval": null,
    "linkmarkers": null,
    "image_url": "https://images.ygoprodeck.com/images/cards/11264180.jpg",
    "image_url_small": "https://images.ygoprodeck.com/images/cards_small/11264180.jpg",
    "image_url_cropped": "https://images.ygoprodeck.com/images/cards_cropped/11264180.jpg"
}