{
    "id": 62892347,
    "name": "Arcana Force 0 - The Fool",
    "type": "Effect Monster",
    "desc": "This card cannot be destroyed by battle. This card cannot be changed to Defense Position, except with a card effect. When this card is Summoned: Toss a coin and gain the appropriate effect. \u25cf Heads: Negate your card effects that target this card, and destroy them. \u25cf Tails: Negate your opponent's card effects that target this card, and destroy them.",
    "atk": 0,
    "def": 0,
    "level": 1,
    "race": "Fairy",
    "attribute": "LIGHT",
    "scale": null,
    "archetype": "Arcana Force",
    "linkval": null,
    "linkmarkers": null,
    "image_url": "https://images.ygoprodeck.com/images/cards/62892347.jpg",
    "image_url_small": "https://images.ygoprodeck.com/images/cards_small/62892347.jpg",
    "image_url_cropped": "https://images.ygoprodeck.com/images/cards_cropped/62892347.jpg"
}