{
    "id": 51481927,
    "name": "Spell Absorption",
    "type": "Spell Card",
    "desc": "Each time a Spell Card is activated, gain 500 LP immediately after it resolves.",
    "atk": null,
    "def": null,
    "level": null,
    "race": "Continuous",
    "attribute": null,
    "scale": null,
    "archetype": null,
    "linkval": null,
    "linkmarkers": null,
    "image_url": "https://images.ygoprodeck.com/images/cards/51481927.jpg",
    "image_url_small": "https://images.ygoprodeck.com/images/cards_small/51481927.jpg",
    "image_url_cropped": "https://images.ygoprodeck.com/images/cards_cropped/51481927.jpg"
}