{
    "id": 11317977,
    "name": "Lunalight Black Sheep",
    "type": "Effect Monster",
    "desc": "You can discard this card, then activate 1 of these effects;\n\u25cf Add 1 \"Lunalight\" monster from your Graveyard to your hand, except \"Lunalight Black Sheep\".\n\u25cf Add 1 \"Polymerization\" from your Deck to your hand.\nIf this card is sent to the Graveyard as a Fusion Material for a Fusion Summon: You can add to your hand, 1 face-up \"Lunalight\" Pendulum Monster from your Extra Deck or 1 \"Lunalight\" monster from your Graveyard, except \"Lunalight Black Sheep\".",
    "atk": 100,
    "def": 600,
    "level": 2,
    "race": "Beast-Warrior",
    "attribute": "DARK",
    "scale": null,
    "archetype": "Lunalight",
    "linkval": null,
    "linkmarkers": null,
    "image_url": "https://images.ygoprodeck.com/images/cards/11317977.jpg",
    "image_url_small": "https://images.ygoprodeck.com/images/cards_small/11317977.jpg",
    "image_url_cropped": "https://images.ygoprodeck.com/images/cards_cropped/11317977.jpg"
}