{
    "id": 53466826,
    "name": "Heroic Chance",
    "type": "Spell Card",
    "desc": "Target 1 face-up \"Heroic\" monster you control; this turn, double its ATK, but it cannot attack your opponent directly. You can only activate 1 \"Heroic Chance\" per turn.",
    "atk": null,
    "def": null,
    "level": null,
    "race": "Normal",
    "attribute": null,
    "scale": null,
    "archetype": "Heroic",
    "linkval": null,
    "linkmarkers": null,
    "image_url": "https://images.ygoprodeck.com/images/cards/53466826.jpg",
    "image_url_small": "https://images.ygoprodeck.com/images/cards_small/53466826.jpg",
    "image_url_cropped": "https://images.ygoprodeck.com/images/cards_cropped/53466826.jpg"
}