{
    "id": 49258578,
    "name": "Gate Deeg",
    "type": "Normal Monster",
    "desc": "This weird monster has a portal in its belly that brings reinforcements from the farthest reaches of the netherworld.",
    "atk": 700,
    "def": 800,
    "level": 3,
    "race": "Beast",
    "attribute": "DARK",
    "scale": null,
    "archetype": null,
    "linkval": null,
    "linkmarkers": null,
    "image_url": "https://images.ygoprodeck.com/images/cards/49258578.jpg",
    "image_url_small": "https://images.ygoprodeck.com/images/cards_small/49258578.jpg",
    "image_url_cropped": "https://images.ygoprodeck.com/images/cards_cropped/49258578.jpg"
}