{
    "id": 29905795,
    "name": "The Fabled Chawa",
    "typeline": [
        "Beast",
        "Tuner",
        "Effect"
    ],
    "type": "Tuner Monster",
    "humanReadableCardType": "Tuner Effect Monster",
    "frameType": "effect",
    "desc": "During your Main Phase: You can activate this effect; discard 1 \"Fabled\" monster, and if you do, Special Summon this card from your hand.",
    "race": "Beast",
    "atk": 200,
    "def": 100,
    "level": 1,
    "attribute": "LIGHT",
    "archetype": "Fabled",
    "ygoprodeck_url": "https://ygoprodeck.com/card/the-fabled-chawa-2534",
    "card_sets": [
        {
            "set_name": "Duel Terminal 4",
            "set_code": "DT04-EN016",
            "set_rarity": "Duel Terminal Normal Parallel Rare",
            "set_rarity_code": "(DNPR)",
            "set_price": "0"
        },
        {
            "set_name": "Hidden Arsenal 4: Trishula's Triumph",
            "set_code": "HA04-EN006",
            "set_rarity": "Super Rare",
            "set_rarity_code": "(SR)",
            "set_price": "0"
        },
        {
            "set_name": "Hidden Arsenal: Chapter 1",
            "set_code": "HAC1-EN136",
            "set_rarity": "Common",
            "set_rarity_code": "(C)",
            "set_price": "0"
        },
        {
            "set_name": "Hidden Arsenal: Chapter 1",
            "set_code": "HAC1-EN136",
            "set_rarity": "Duel Terminal Normal Parallel Rare",
            "set_rarity_code": "(DNPR)",
            "set_price": "1.28"
        },
        {
            "set_name": "OTS Tournament Pack 15 (POR)",
            "set_code": "OP15-PT034",
            "set_rarity": "Common",
            "set_rarity_code": "(C)",
            "set_price": "0"
        }
    ],
    "card_images": [
        {
            "id": 29905795,
            "image_url": "https://images.ygoprodeck.com/images/cards/29905795.jpg",
            "image_url_small": "https://images.ygoprodeck.com/images/cards_small/29905795.jpg",
            "image_url_cropped": "https://images.ygoprodeck.com/images/cards_cropped/29905795.jpg"
        }
    ],
    "card_prices": [
        {
            "cardmarket_price": "0.02",
            "tcgplayer_price": "0.19",
            "ebay_price": "0.99",
            "amazon_price": "0.49",
            "coolstuffinc_price": "0.49"
        }
    ]
}