{
    "id": 51365514,
    "name": "Hieratic Seal of Supremacy",
    "type": "Spell Card",
    "desc": "Special Summon 1 \"Hieratic\" monster from your hand.",
    "atk": null,
    "def": null,
    "level": null,
    "race": "Normal",
    "attribute": null,
    "scale": null,
    "archetype": "Hieratic",
    "linkval": null,
    "linkmarkers": null,
    "image_url": "https://images.ygoprodeck.com/images/cards/51365514.jpg",
    "image_url_small": "https://images.ygoprodeck.com/images/cards_small/51365514.jpg",
    "image_url_cropped": "https://images.ygoprodeck.com/images/cards_cropped/51365514.jpg"
}