{
    "id": 22123627,
    "name": "Moray of Greed",
    "type": "Spell Card",
    "desc": "Shuffle 2 WATER monsters from your hand into the Deck, then draw 3 cards.",
    "atk": null,
    "def": null,
    "level": null,
    "race": "Normal",
    "attribute": null,
    "scale": null,
    "archetype": "Greed",
    "linkval": null,
    "linkmarkers": null,
    "image_url": "https://images.ygoprodeck.com/images/cards/22123627.jpg",
    "image_url_small": "https://images.ygoprodeck.com/images/cards_small/22123627.jpg",
    "image_url_cropped": "https://images.ygoprodeck.com/images/cards_cropped/22123627.jpg"
}