{
    "id": 72869010,
    "name": "Soul Hunter",
    "type": "Fusion Monster",
    "desc": "\"Lord of the Lamp\" + \"Invader from Another Dimension\"",
    "atk": 2200,
    "def": 1800,
    "level": 6,
    "race": "Fiend",
    "attribute": "DARK",
    "scale": null,
    "archetype": null,
    "linkval": null,
    "linkmarkers": null,
    "image_url": "https://images.ygoprodeck.com/images/cards/72869010.jpg",
    "image_url_small": "https://images.ygoprodeck.com/images/cards_small/72869010.jpg",
    "image_url_cropped": "https://images.ygoprodeck.com/images/cards_cropped/72869010.jpg"
}