{
    "id": 62193699,
    "name": "Rock Ogre Grotto #2",
    "type": "Normal Monster",
    "desc": "A golem formed by boulders, this monster turns its enemies to stone and crushes them to dust.",
    "atk": 700,
    "def": 1400,
    "level": 3,
    "race": "Rock",
    "attribute": "EARTH",
    "scale": null,
    "archetype": null,
    "linkval": null,
    "linkmarkers": null,
    "image_url": "https://images.ygoprodeck.com/images/cards/62193699.jpg",
    "image_url_small": "https://images.ygoprodeck.com/images/cards_small/62193699.jpg",
    "image_url_cropped": "https://images.ygoprodeck.com/images/cards_cropped/62193699.jpg"
}