{
    "id": 56413937,
    "name": "Warrior of Tradition",
    "type": "Fusion Monster",
    "desc": "\"Sonic Maid\" + \"Beautiful Headhuntress\"",
    "atk": 1900,
    "def": 1700,
    "level": 6,
    "race": "Warrior",
    "attribute": "EARTH",
    "scale": null,
    "archetype": null,
    "linkval": null,
    "linkmarkers": null,
    "image_url": "https://images.ygoprodeck.com/images/cards/56413937.jpg",
    "image_url_small": "https://images.ygoprodeck.com/images/cards_small/56413937.jpg",
    "image_url_cropped": "https://images.ygoprodeck.com/images/cards_cropped/56413937.jpg"
}