{
    "id": 50277355,
    "name": "Cross-Sheep",
    "typeline": [
        "Beast",
        "Link",
        "Effect"
    ],
    "type": "Link Monster",
    "humanReadableCardType": "Link Effect Monster",
    "frameType": "link",
    "desc": "2 monsters with different names\r\nIf a monster is Special Summoned to a zone this card points to: You can apply the following effects, in sequence, based on the card types of the monster(s) this card points to.\r\n\u25cf Ritual: Draw 2 cards, then discard 2 cards. \u25cf Fusion: Special Summon 1 Level 4 or lower monster from your GY. \u25cf Synchro: All monsters you control gain 700 ATK. \u25cf Xyz: All monsters your opponent controls lose 700 ATK.\r\nYou can only use this effect of \"Cross-Sheep\" once per turn.",
    "race": "Beast",
    "atk": 700,
    "def": null,
    "level": null,
    "attribute": "EARTH",
    "linkval": 2,
    "linkmarkers": [
        "Bottom-Left",
        "Bottom-Right"
    ],
    "ygoprodeck_url": "https://ygoprodeck.com/card/cross-sheep-10668",
    "card_sets": [
        {
            "set_name": "2021 Tin of Ancient Battles",
            "set_code": "MP21-EN018",
            "set_rarity": "Prismatic Secret Rare",
            "set_rarity_code": "(PScR)",
            "set_price": "0"
        },
        {
            "set_name": "Battles of Legend: Armageddon",
            "set_code": "BLAR-EN092",
            "set_rarity": "Ultra Rare",
            "set_rarity_code": "(UR)",
            "set_price": "0"
        },
        {
            "set_name": "Ignition Assault",
            "set_code": "IGAS-EN047",
            "set_rarity": "Rare",
            "set_rarity_code": "(R)",
            "set_price": "0"
        }
    ],
    "card_images": [
        {
            "id": 50277355,
            "image_url": "https://images.ygoprodeck.com/images/cards/50277355.jpg",
            "image_url_small": "https://images.ygoprodeck.com/images/cards_small/50277355.jpg",
            "image_url_cropped": "https://images.ygoprodeck.com/images/cards_cropped/50277355.jpg"
        }
    ],
    "card_prices": [
        {
            "cardmarket_price": "0.45",
            "tcgplayer_price": "2.12",
            "ebay_price": "3.45",
            "amazon_price": "1.39",
            "coolstuffinc_price": "0.99"
        }
    ]
}