{
    "id": 423585,
    "name": "Summoner Monk",
    "type": "Effect Monster",
    "desc": "While this card is face-up on the field, it cannot be Tributed. If this card is Normal or Flip Summoned: Change this card to Defense Position. Once per turn: You can discard 1 Spell; Special Summon 1 Level 4 monster from your Deck, but that monster cannot attack this turn.",
    "atk": 800,
    "def": 1600,
    "level": 4,
    "race": "Spellcaster",
    "attribute": "DARK",
    "scale": null,
    "archetype": null,
    "linkval": null,
    "linkmarkers": null,
    "image_url": "https://images.ygoprodeck.com/images/cards/423585.jpg",
    "image_url_small": "https://images.ygoprodeck.com/images/cards_small/423585.jpg",
    "image_url_cropped": "https://images.ygoprodeck.com/images/cards_cropped/423585.jpg"
}