{
    "id": 84523092,
    "name": "Witchcrafter Haine",
    "type": "Effect Monster",
    "desc": "Your opponent cannot target other Spellcaster monsters you control with card effects. (Quick Effect): You can discard 1 Spell, then target 1 face-up card your opponent controls; destroy it. You can only use this effect of \"Witchcrafter Haine\" once per turn.",
    "atk": 2400,
    "def": 1000,
    "level": 7,
    "race": "Spellcaster",
    "attribute": "DARK",
    "scale": null,
    "archetype": "Witchcrafter",
    "linkval": null,
    "linkmarkers": null,
    "image_url": "https://images.ygoprodeck.com/images/cards/84523092.jpg",
    "image_url_small": "https://images.ygoprodeck.com/images/cards_small/84523092.jpg",
    "image_url_cropped": "https://images.ygoprodeck.com/images/cards_cropped/84523092.jpg"
}