{
    "id": 27285068,
    "name": "Theorealize Liberation",
    "type": "Spell Card",
    "humanReadableCardType": "Quick-Play Spell",
    "frameType": "spell",
    "desc": "If you control \"Medius the Pure\": Add to your hand or Special Summon 1 monster with 300 ATK/200 DEF from your Deck. During your Main Phase: You can banish this card from your GY, then target 1 face-up monster you control; it is treated as a Tuner this turn. You can only use each effect of \"Theorealize Liberation\" once per turn.",
    "race": "Quick-Play",
    "archetype": "Theorealize",
    "ygoprodeck_url": "https://ygoprodeck.com/card/theorealize-liberation-15341",
    "card_sets": [
        {
            "set_name": "Burst Protocol",
            "set_code": "BPRO-EN058",
            "set_rarity": "Common",
            "set_rarity_code": "(C)",
            "set_price": "0"
        }
    ],
    "card_images": [
        {
            "id": 27285068,
            "image_url": "https://images.ygoprodeck.com/images/cards/27285068.jpg",
            "image_url_small": "https://images.ygoprodeck.com/images/cards_small/27285068.jpg",
            "image_url_cropped": "https://images.ygoprodeck.com/images/cards_cropped/27285068.jpg"
        }
    ],
    "card_prices": [
        {
            "cardmarket_price": "0.14",
            "tcgplayer_price": "0.81",
            "ebay_price": "0.00",
            "amazon_price": "0.00",
            "coolstuffinc_price": "0.00"
        }
    ]
}