{
    "id": 101305006,
    "name": "Hamon, Lord of Striking Thunder - Sacred Beast of Sinful Catastrophe",
    "typeline": [
        "Thunder",
        "Effect"
    ],
    "type": "Effect Monster",
    "humanReadableCardType": "Effect Monster",
    "frameType": "effect",
    "desc": "Cannot be Normal Summoned/Set. Must be Special Summoned with a \"Sacred Beast\" card. You can reveal this card in your hand; add 1 \"Sacred Beast\" Spell from your Deck to your hand, then discard 1 card. You can only use this effect of \"Hamon, Lord of Striking Thunder - Sacred Beast of Sinful Catastrophe\" once per turn. Once per turn, if a monster(s) is sent to your opponent's GY: Inflict 1000 damage to your opponent. If this card is destroyed by battle or card effect: You can activate this effect; you take no damage this turn.",
    "race": "Thunder",
    "atk": 4000,
    "def": 4000,
    "level": 10,
    "attribute": "LIGHT",
    "archetype": "Phantasm",
    "ygoprodeck_url": "https://ygoprodeck.com/card/hamon-lord-of-striking-thunder-sacred-beast-of-sinful-catastrophe-15602",
    "card_images": [
        {
            "id": 101305006,
            "image_url": "https://images.ygoprodeck.com/images/cards/101305006.jpg",
            "image_url_small": "https://images.ygoprodeck.com/images/cards_small/101305006.jpg",
            "image_url_cropped": "https://images.ygoprodeck.com/images/cards_cropped/101305006.jpg"
        }
    ],
    "card_prices": [
        {
            "cardmarket_price": "0.00",
            "tcgplayer_price": "0.00",
            "ebay_price": "0.00",
            "amazon_price": "0.00",
            "coolstuffinc_price": "0.00"
        }
    ]
}