{
    "id": 56387350,
    "name": "Vampire Baby",
    "type": "Effect Monster",
    "desc": "At the end of the Battle Phase, if this card destroyed a monster by battle and sent it to the Graveyard this turn: You can Special Summon that monster to your side of the field.",
    "atk": 700,
    "def": 1000,
    "level": 3,
    "race": "Zombie",
    "attribute": "DARK",
    "scale": null,
    "archetype": "Vampire",
    "linkval": null,
    "linkmarkers": null,
    "image_url": "https://images.ygoprodeck.com/images/cards/56387350.jpg",
    "image_url_small": "https://images.ygoprodeck.com/images/cards_small/56387350.jpg",
    "image_url_cropped": "https://images.ygoprodeck.com/images/cards_cropped/56387350.jpg"
}