{
    "id": 73787254,
    "name": "Saber Vault",
    "type": "Spell Card",
    "desc": "Each face-up \"X-Saber\" monster on the field gains 100 ATK x its Level, and loses 100 DEF x its Level.",
    "atk": null,
    "def": null,
    "level": null,
    "race": "Field",
    "attribute": null,
    "scale": null,
    "archetype": "X-Saber",
    "linkval": null,
    "linkmarkers": null,
    "image_url": "https://images.ygoprodeck.com/images/cards/73787254.jpg",
    "image_url_small": "https://images.ygoprodeck.com/images/cards_small/73787254.jpg",
    "image_url_cropped": "https://images.ygoprodeck.com/images/cards_cropped/73787254.jpg"
}