{
    "id": 33655493,
    "name": "Belial - Marquis of Darkness",
    "type": "Effect Monster",
    "desc": "Your opponent cannot target any face-up monster you control, except \"Belial - Marquis of Darkness\", for an attack, or with Spell/Trap effects.",
    "atk": 2800,
    "def": 2400,
    "level": 8,
    "race": "Fiend",
    "attribute": "DARK",
    "scale": null,
    "archetype": null,
    "linkval": null,
    "linkmarkers": null,
    "image_url": "https://images.ygoprodeck.com/images/cards/33655493.jpg",
    "image_url_small": "https://images.ygoprodeck.com/images/cards_small/33655493.jpg",
    "image_url_cropped": "https://images.ygoprodeck.com/images/cards_cropped/33655493.jpg"
}