{
    "id": 212652,
    "name": "Trap of the Poisonous Scorpion",
    "type": "Trap Card",
    "humanReadableCardType": "Normal Trap",
    "frameType": "trap",
    "desc": "When an opponent's monster declares an attack: Destroy it, then inflict 300 damage to your opponent.",
    "race": "Normal",
    "ygoprodeck_url": "https://ygoprodeck.com/card/trap-of-the-poisonous-scorpion-15209",
    "card_images": [
        {
            "id": 212652,
            "image_url": "https://images.ygoprodeck.com/images/cards/212652.jpg",
            "image_url_small": "https://images.ygoprodeck.com/images/cards_small/212652.jpg",
            "image_url_cropped": "https://images.ygoprodeck.com/images/cards_cropped/212652.jpg"
        }
    ],
    "card_prices": [
        {
            "cardmarket_price": "0.00",
            "tcgplayer_price": "0.00",
            "ebay_price": "0.00",
            "amazon_price": "0.00",
            "coolstuffinc_price": "0.00"
        }
    ]
}