{
    "id": 72842870,
    "name": "Tyhone",
    "type": "Normal Monster",
    "desc": "Capable of firing cannonballs from its mouth for long-range attacks, this creature is particularly effective in mountain battles.",
    "atk": 1200,
    "def": 1400,
    "level": 4,
    "race": "Winged Beast",
    "attribute": "WIND",
    "scale": null,
    "archetype": null,
    "linkval": null,
    "linkmarkers": null,
    "image_url": "https://images.ygoprodeck.com/images/cards/72842870.jpg",
    "image_url_small": "https://images.ygoprodeck.com/images/cards_small/72842870.jpg",
    "image_url_cropped": "https://images.ygoprodeck.com/images/cards_cropped/72842870.jpg"
}