{
    "id": 42591472,
    "name": "Laughing Flower",
    "typeline": [
        "Plant",
        "Normal"
    ],
    "type": "Normal Monster",
    "humanReadableCardType": "Normal Monster",
    "frameType": "normal",
    "desc": "''A flower whose laugh can confuse the minds of enemies.''",
    "race": "Plant",
    "atk": 900,
    "def": 500,
    "level": 2,
    "attribute": "EARTH",
    "ygoprodeck_url": "https://ygoprodeck.com/card/laughing-flower-3631",
    "card_images": [
        {
            "id": 42591472,
            "image_url": "https://images.ygoprodeck.com/images/cards/42591472.jpg",
            "image_url_small": "https://images.ygoprodeck.com/images/cards_small/42591472.jpg",
            "image_url_cropped": "https://images.ygoprodeck.com/images/cards_cropped/42591472.jpg"
        }
    ],
    "card_prices": [
        {
            "cardmarket_price": "0.16",
            "tcgplayer_price": "0.00",
            "ebay_price": "4.00",
            "amazon_price": "0.00",
            "coolstuffinc_price": "0.00"
        }
    ]
}