{
    "id": 40133511,
    "name": "Bazoo the Soul-Eater",
    "type": "Effect Monster",
    "desc": "Once per turn: You can banish up to 3 monsters from your Graveyard; this card gains 300 ATK for each, until the end of your opponent's turn.",
    "atk": 1600,
    "def": 900,
    "level": 4,
    "race": "Beast",
    "attribute": "EARTH",
    "scale": null,
    "archetype": null,
    "linkval": null,
    "linkmarkers": null,
    "image_url": "https://images.ygoprodeck.com/images/cards/40133511.jpg",
    "image_url_small": "https://images.ygoprodeck.com/images/cards_small/40133511.jpg",
    "image_url_cropped": "https://images.ygoprodeck.com/images/cards_cropped/40133511.jpg"
}